bert/__init__.py
bert/attention.py
bert/embeddings.py
bert/layer.py
bert/loader.py
bert/loader_albert.py
bert/model.py
bert/transformer.py
bert/version.py
bert/tokenization/__init__.py
bert/tokenization/albert_tokenization.py
bert/tokenization/bert_tokenization.py
tests/ext/__init__.py
tests/ext/modeling.py
tests/nonci/__init__.py
tests/nonci/test_attention.py
tests/nonci/test_bert.py
tests/nonci/test_compare_pretrained.py
tests/nonci/test_load_pretrained_weights.py
tests/nonci/test_multi_lang.py
tests/nonci/test_stock_weights.py
tests/nonci/test_transformer.py
bert_for_tf2e-0.14.13.dist-info/LICENSE
bert_for_tf2e-0.14.13.dist-info/METADATA
bert_for_tf2e-0.14.13.dist-info/WHEEL
bert_for_tf2e-0.14.13.dist-info/top_level.txt
bert_for_tf2e-0.14.13.dist-info/zip-safe
bert_for_tf2e-0.14.13.dist-info/RECORD
